<?xml version="1.0" encoding="UTF-8"?>
<config xmlns="http://www.knime.org/2008/09/XMLConfig" xmlns:xsi="http://www.w3.org/2001/XMLSchema-instance" xsi:schemaLocation="http://www.knime.org/2008/09/XMLConfig http://www.knime.org/XMLConfig_2008_09.xsd" key="spec.xml">
<entry key="spec_name" type="xstring" value="default"/>
<entry key="number_columns" type="xint" value="16"/>
<config key="column_spec_0">
<entry key="column_name" type="xstring" value="id"/>
<config key="element_names">
<entry key="array-size" type="xint" value="0"/>
</config>
<config key="column_type">
<entry key="cell_class" type="xstring" value="org.knime.core.data.def.StringCell"/>
</config>
<config key="column_domain">
<config key="possible_values">
<entry key="array-size" type="xint" value="49"/>
<config key="0">
<entry key="datacell" type="xstring" value="org.knime.core.data.def.StringCell"/>
<config key="org.knime.core.data.def.StringCell">
<entry key="StringCell" type="xstring" value="32492124910"/>
</config>
</config>
<config key="1">
<entry key="datacell" type="xstring" value="org.knime.core.data.def.StringCell"/>
<config key="org.knime.core.data.def.StringCell">
<entry key="StringCell" type="xstring" value="32492124630"/>
</config>
</config>
<config key="2">
<entry key="datacell" type="xstring" value="org.knime.core.data.def.StringCell"/>
<config key="org.knime.core.data.def.StringCell">
<entry key="StringCell" type="xstring" value="32684719882"/>
</config>
</config>
<config key="3">
<entry key="datacell" type="xstring" value="org.knime.core.data.def.StringCell"/>
<config key="org.knime.core.data.def.StringCell">
<entry key="StringCell" type="xstring" value="32711653421"/>
</config>
</config>
<config key="4">
<entry key="datacell" type="xstring" value="org.knime.core.data.def.StringCell"/>
<config key="org.knime.core.data.def.StringCell">
<entry key="StringCell" type="xstring" value="32794179516"/>
</config>
</config>
<config key="5">
<entry key="datacell" type="xstring" value="org.knime.core.data.def.StringCell"/>
<config key="org.knime.core.data.def.StringCell">
<entry key="StringCell" type="xstring" value="32793497096"/>
</config>
</config>
<config key="6">
<entry key="datacell" type="xstring" value="org.knime.core.data.def.StringCell"/>
<config key="org.knime.core.data.def.StringCell">
<entry key="StringCell" type="xstring" value="32019911223"/>
</config>
</config>
<config key="7">
<entry key="datacell" type="xstring" value="org.knime.core.data.def.StringCell"/>
<config key="org.knime.core.data.def.StringCell">
<entry key="StringCell" type="xstring" value="32751976795"/>
</config>
</config>
<config key="8">
<entry key="datacell" type="xstring" value="org.knime.core.data.def.StringCell"/>
<config key="org.knime.core.data.def.StringCell">
<entry key="StringCell" type="xstring" value="32576142522"/>
</config>
</config>
<config key="9">
<entry key="datacell" type="xstring" value="org.knime.core.data.def.StringCell"/>
<config key="org.knime.core.data.def.StringCell">
<entry key="StringCell" type="xstring" value="32578621252"/>
</config>
</config>
<config key="10">
<entry key="datacell" type="xstring" value="org.knime.core.data.def.StringCell"/>
<config key="org.knime.core.data.def.StringCell">
<entry key="StringCell" type="xstring" value="32578595162"/>
</config>
</config>
<config key="11">
<entry key="datacell" type="xstring" value="org.knime.core.data.def.StringCell"/>
<config key="org.knime.core.data.def.StringCell">
<entry key="StringCell" type="xstring" value="31883480204"/>
</config>
</config>
<config key="12">
<entry key="datacell" type="xstring" value="org.knime.core.data.def.StringCell"/>
<config key="org.knime.core.data.def.StringCell">
<entry key="StringCell" type="xstring" value="32682596786"/>
</config>
</config>
<config key="13">
<entry key="datacell" type="xstring" value="org.knime.core.data.def.StringCell"/>
<config key="org.knime.core.data.def.StringCell">
<entry key="StringCell" type="xstring" value="31691936504"/>
</config>
</config>
<config key="14">
<entry key="datacell" type="xstring" value="org.knime.core.data.def.StringCell"/>
<config key="org.knime.core.data.def.StringCell">
<entry key="StringCell" type="xstring" value="31624036203"/>
</config>
</config>
<config key="15">
<entry key="datacell" type="xstring" value="org.knime.core.data.def.StringCell"/>
<config key="org.knime.core.data.def.StringCell">
<entry key="StringCell" type="xstring" value="32395838596"/>
</config>
</config>
<config key="16">
<entry key="datacell" type="xstring" value="org.knime.core.data.def.StringCell"/>
<config key="org.knime.core.data.def.StringCell">
<entry key="StringCell" type="xstring" value="31592604764"/>
</config>
</config>
<config key="17">
<entry key="datacell" type="xstring" value="org.knime.core.data.def.StringCell"/>
<config key="org.knime.core.data.def.StringCell">
<entry key="StringCell" type="xstring" value="31592599514"/>
</config>
</config>
<config key="18">
<entry key="datacell" type="xstring" value="org.knime.core.data.def.StringCell"/>
<config key="org.knime.core.data.def.StringCell">
<entry key="StringCell" type="xstring" value="32435650575"/>
</config>
</config>
<config key="19">
<entry key="datacell" type="xstring" value="org.knime.core.data.def.StringCell"/>
<config key="org.knime.core.data.def.StringCell">
<entry key="StringCell" type="xstring" value="32314791961"/>
</config>
</config>
<config key="20">
<entry key="datacell" type="xstring" value="org.knime.core.data.def.StringCell"/>
<config key="org.knime.core.data.def.StringCell">
<entry key="StringCell" type="xstring" value="31624006813"/>
</config>
</config>
<config key="21">
<entry key="datacell" type="xstring" value="org.knime.core.data.def.StringCell"/>
<config key="org.knime.core.data.def.StringCell">
<entry key="StringCell" type="xstring" value="32395807656"/>
</config>
</config>
<config key="22">
<entry key="datacell" type="xstring" value="org.knime.core.data.def.StringCell"/>
<config key="org.knime.core.data.def.StringCell">
<entry key="StringCell" type="xstring" value="32314775721"/>
</config>
</config>
<config key="23">
<entry key="datacell" type="xstring" value="org.knime.core.data.def.StringCell"/>
<config key="org.knime.core.data.def.StringCell">
<entry key="StringCell" type="xstring" value="32057774000"/>
</config>
</config>
<config key="24">
<entry key="datacell" type="xstring" value="org.knime.core.data.def.StringCell"/>
<config key="org.knime.core.data.def.StringCell">
<entry key="StringCell" type="xstring" value="32314770101"/>
</config>
</config>
<config key="25">
<entry key="datacell" type="xstring" value="org.knime.core.data.def.StringCell"/>
<config key="org.knime.core.data.def.StringCell">
<entry key="StringCell" type="xstring" value="32435626365"/>
</config>
</config>
<config key="26">
<entry key="datacell" type="xstring" value="org.knime.core.data.def.StringCell"/>
<config key="org.knime.core.data.def.StringCell">
<entry key="StringCell" type="xstring" value="32057756090"/>
</config>
</config>
<config key="27">
<entry key="datacell" type="xstring" value="org.knime.core.data.def.StringCell"/>
<config key="org.knime.core.data.def.StringCell">
<entry key="StringCell" type="xstring" value="32057747630"/>
</config>
</config>
<config key="28">
<entry key="datacell" type="xstring" value="org.knime.core.data.def.StringCell"/>
<config key="org.knime.core.data.def.StringCell">
<entry key="StringCell" type="xstring" value="31623969553"/>
</config>
</config>
<config key="29">
<entry key="datacell" type="xstring" value="org.knime.core.data.def.StringCell"/>
<config key="org.knime.core.data.def.StringCell">
<entry key="StringCell" type="xstring" value="32435589295"/>
</config>
</config>
<config key="30">
<entry key="datacell" type="xstring" value="org.knime.core.data.def.StringCell"/>
<config key="org.knime.core.data.def.StringCell">
<entry key="StringCell" type="xstring" value="32435581585"/>
</config>
</config>
<config key="31">
<entry key="datacell" type="xstring" value="org.knime.core.data.def.StringCell"/>
<config key="org.knime.core.data.def.StringCell">
<entry key="StringCell" type="xstring" value="32314717031"/>
</config>
</config>
<config key="32">
<entry key="datacell" type="xstring" value="org.knime.core.data.def.StringCell"/>
<config key="org.knime.core.data.def.StringCell">
<entry key="StringCell" type="xstring" value="32284450682"/>
</config>
</config>
<config key="33">
<entry key="datacell" type="xstring" value="org.knime.core.data.def.StringCell"/>
<config key="org.knime.core.data.def.StringCell">
<entry key="StringCell" type="xstring" value="31623934023"/>
</config>
</config>
<config key="34">
<entry key="datacell" type="xstring" value="org.knime.core.data.def.StringCell"/>
<config key="org.knime.core.data.def.StringCell">
<entry key="StringCell" type="xstring" value="31623928313"/>
</config>
</config>
<config key="35">
<entry key="datacell" type="xstring" value="org.knime.core.data.def.StringCell"/>
<config key="org.knime.core.data.def.StringCell">
<entry key="StringCell" type="xstring" value="31623914603"/>
</config>
</config>
<config key="36">
<entry key="datacell" type="xstring" value="org.knime.core.data.def.StringCell"/>
<config key="org.knime.core.data.def.StringCell">
<entry key="StringCell" type="xstring" value="31592493714"/>
</config>
</config>
<config key="37">
<entry key="datacell" type="xstring" value="org.knime.core.data.def.StringCell"/>
<config key="org.knime.core.data.def.StringCell">
<entry key="StringCell" type="xstring" value="31623901673"/>
</config>
</config>
<config key="38">
<entry key="datacell" type="xstring" value="org.knime.core.data.def.StringCell"/>
<config key="org.knime.core.data.def.StringCell">
<entry key="StringCell" type="xstring" value="32284426502"/>
</config>
</config>
<config key="39">
<entry key="datacell" type="xstring" value="org.knime.core.data.def.StringCell"/>
<config key="org.knime.core.data.def.StringCell">
<entry key="StringCell" type="xstring" value="32284422352"/>
</config>
</config>
<config key="40">
<entry key="datacell" type="xstring" value="org.knime.core.data.def.StringCell"/>
<config key="org.knime.core.data.def.StringCell">
<entry key="StringCell" type="xstring" value="32057663120"/>
</config>
</config>
<config key="41">
<entry key="datacell" type="xstring" value="org.knime.core.data.def.StringCell"/>
<config key="org.knime.core.data.def.StringCell">
<entry key="StringCell" type="xstring" value="32057625310"/>
</config>
</config>
<config key="42">
<entry key="datacell" type="xstring" value="org.knime.core.data.def.StringCell"/>
<config key="org.knime.core.data.def.StringCell">
<entry key="StringCell" type="xstring" value="32435429975"/>
</config>
</config>
<config key="43">
<entry key="datacell" type="xstring" value="org.knime.core.data.def.StringCell"/>
<config key="org.knime.core.data.def.StringCell">
<entry key="StringCell" type="xstring" value="32333396906"/>
</config>
</config>
<config key="44">
<entry key="datacell" type="xstring" value="org.knime.core.data.def.StringCell"/>
<config key="org.knime.core.data.def.StringCell">
<entry key="StringCell" type="xstring" value="32372540845"/>
</config>
</config>
<config key="45">
<entry key="datacell" type="xstring" value="org.knime.core.data.def.StringCell"/>
<config key="org.knime.core.data.def.StringCell">
<entry key="StringCell" type="xstring" value="32372538015"/>
</config>
</config>
<config key="46">
<entry key="datacell" type="xstring" value="org.knime.core.data.def.StringCell"/>
<config key="org.knime.core.data.def.StringCell">
<entry key="StringCell" type="xstring" value="32333395286"/>
</config>
</config>
<config key="47">
<entry key="datacell" type="xstring" value="org.knime.core.data.def.StringCell"/>
<config key="org.knime.core.data.def.StringCell">
<entry key="StringCell" type="xstring" value="32222255162"/>
</config>
</config>
<config key="48">
<entry key="datacell" type="xstring" value="org.knime.core.data.def.StringCell"/>
<config key="org.knime.core.data.def.StringCell">
<entry key="StringCell" type="xstring" value="31561372903"/>
</config>
</config>
</config>
</config>
<config key="column_properties"/>
<config key="meta_data"/>
</config>
<config key="column_spec_1">
<entry key="column_name" type="xstring" value="user"/>
<config key="element_names">
<entry key="array-size" type="xint" value="0"/>
</config>
<config key="column_type">
<entry key="cell_class" type="xstring" value="org.knime.core.data.def.StringCell"/>
</config>
<config key="column_domain">
<config key="possible_values">
<entry key="array-size" type="xint" value="9"/>
<config key="0">
<entry key="datacell" type="xstring" value="org.knime.core.data.def.StringCell"/>
<config key="org.knime.core.data.def.StringCell">
<entry key="StringCell" type="xstring" value="46191841@N00"/>
</config>
</config>
<config key="1">
<entry key="datacell" type="xstring" value="org.knime.core.data.def.StringCell"/>
<config key="org.knime.core.data.def.StringCell">
<entry key="StringCell" type="xstring" value="7759978@N04"/>
</config>
</config>
<config key="2">
<entry key="datacell" type="xstring" value="org.knime.core.data.def.StringCell"/>
<config key="org.knime.core.data.def.StringCell">
<entry key="StringCell" type="xstring" value="15917364@N02"/>
</config>
</config>
<config key="3">
<entry key="datacell" type="xstring" value="org.knime.core.data.def.StringCell"/>
<config key="org.knime.core.data.def.StringCell">
<entry key="StringCell" type="xstring" value="128069291@N04"/>
</config>
</config>
<config key="4">
<entry key="datacell" type="xstring" value="org.knime.core.data.def.StringCell"/>
<config key="org.knime.core.data.def.StringCell">
<entry key="StringCell" type="xstring" value="132072072@N08"/>
</config>
</config>
<config key="5">
<entry key="datacell" type="xstring" value="org.knime.core.data.def.StringCell"/>
<config key="org.knime.core.data.def.StringCell">
<entry key="StringCell" type="xstring" value="41746313@N04"/>
</config>
</config>
<config key="6">
<entry key="datacell" type="xstring" value="org.knime.core.data.def.StringCell"/>
<config key="org.knime.core.data.def.StringCell">
<entry key="StringCell" type="xstring" value="24968900@N08"/>
</config>
</config>
<config key="7">
<entry key="datacell" type="xstring" value="org.knime.core.data.def.StringCell"/>
<config key="org.knime.core.data.def.StringCell">
<entry key="StringCell" type="xstring" value="56198665@N05"/>
</config>
</config>
<config key="8">
<entry key="datacell" type="xstring" value="org.knime.core.data.def.StringCell"/>
<config key="org.knime.core.data.def.StringCell">
<entry key="StringCell" type="xstring" value="27476137@N04"/>
</config>
</config>
</config>
</config>
<config key="column_properties"/>
<config key="meta_data"/>
</config>
<config key="column_spec_2">
<entry key="column_name" type="xstring" value="lat"/>
<config key="element_names">
<entry key="array-size" type="xint" value="0"/>
</config>
<config key="column_type">
<entry key="cell_class" type="xstring" value="org.knime.core.data.def.DoubleCell"/>
</config>
<config key="column_domain">
<config key="lower_bound">
<entry key="datacell" type="xstring" value="org.knime.core.data.def.DoubleCell"/>
<config key="org.knime.core.data.def.DoubleCell">
<entry key="DoubleCell" type="xdouble" value="45.6552"/>
</config>
</config>
<config key="upper_bound">
<entry key="datacell" type="xstring" value="org.knime.core.data.def.DoubleCell"/>
<config key="org.knime.core.data.def.DoubleCell">
<entry key="DoubleCell" type="xdouble" value="45.85495"/>
</config>
</config>
</config>
<config key="column_properties"/>
<config key="meta_data"/>
</config>
<config key="column_spec_3">
<entry key="column_name" type="xstring" value="long"/>
<config key="element_names">
<entry key="array-size" type="xint" value="0"/>
</config>
<config key="column_type">
<entry key="cell_class" type="xstring" value="org.knime.core.data.def.DoubleCell"/>
</config>
<config key="column_domain">
<config key="lower_bound">
<entry key="datacell" type="xstring" value="org.knime.core.data.def.DoubleCell"/>
<config key="org.knime.core.data.def.DoubleCell">
<entry key="DoubleCell" type="xdouble" value="4.720312"/>
</config>
</config>
<config key="upper_bound">
<entry key="datacell" type="xstring" value="org.knime.core.data.def.DoubleCell"/>
<config key="org.knime.core.data.def.DoubleCell">
<entry key="DoubleCell" type="xdouble" value="5.006709"/>
</config>
</config>
</config>
<config key="column_properties"/>
<config key="meta_data"/>
</config>
<config key="column_spec_4">
<entry key="column_name" type="xstring" value="tags"/>
<config key="element_names">
<entry key="array-size" type="xint" value="0"/>
</config>
<config key="column_type">
<entry key="cell_class" type="xstring" value="org.knime.core.data.def.StringCell"/>
</config>
<config key="column_domain">
<config key="possible_values">
<entry key="array-size" type="xint" value="14"/>
<config key="0">
<entry key="datacell" type="xstring" value="org.knime.core.data.def.StringCell"/>
<config key="org.knime.core.data.def.StringCell">
<entry key="StringCell" type="xstring" value="lyon,auvergnerhônealpes,francia,france,vessel,vessels,barcos,boats"/>
</config>
</config>
<config key="1">
<entry key="datacell" type="xstring" value="org.knime.core.data.def.StringCell"/>
<config key="org.knime.core.data.def.StringCell">
<entry key="StringCell" type="xstring" value="france,lyon,auvergnerhônealpes,francia,puerto,port,harbour,confluence"/>
</config>
</config>
<config key="2">
<entry key="datacell" type="xstring" value="org.knime.core.data.def.StringCell"/>
<config key="org.knime.core.data.def.StringCell">
<entry key="StringCell" type="xstring" value="lyon,rhônealpes,france,francia,mall,shoppingmall,centrocomercial,confluence,night,noche"/>
</config>
</config>
<config key="3">
<entry key="datacell" type="xstring" value="org.knime.core.data.def.StringCell"/>
<config key="org.knime.core.data.def.StringCell">
<entry key="StringCell" type="xstring" value="lyon,rhônealpes,france,francia,portrambaud,puerto,harbour,confluence"/>
</config>
</config>
<config key="4">
<entry key="datacell" type="xstring" value="org.knime.core.data.def.StringCell"/>
<config key="org.knime.core.data.def.StringCell">
<entry key="StringCell" type="xstring" value="coffee,café,terrace,sunny,building,railway,lasucrière,confluence,lyon,france"/>
</config>
</config>
<config key="5">
<entry key="datacell" type="xstring" value="org.knime.core.data.def.StringCell"/>
<config key="org.knime.core.data.def.StringCell">
<entry key="StringCell" type="xstring" value="lyon,rhone,a7,autoroutedusoleil,circulation,traffic,flou,effet,nuit,night,blurred,mouvement,movement,graphisme,abstraction,olympus,omdem5"/>
</config>
</config>
<config key="6">
<entry key="datacell" type="xstring" value="org.knime.core.data.def.StringCell"/>
<config key="org.knime.core.data.def.StringCell">
<entry key="StringCell" type="xstring" value="saony,alpha,slt,a65,sigma,confluence,lyon,paysage,urbain,noir,blanc,black,white"/>
</config>
</config>
<config key="7">
<entry key="datacell" type="xstring" value="org.knime.core.data.def.StringCell"/>
<config key="org.knime.core.data.def.StringCell">
<entry key="StringCell" type="xstring" value="france,fixie,urbain,confluence,lyon,bike,beton"/>
</config>
</config>
<config key="8">
<entry key="datacell" type="xstring" value="org.knime.core.data.def.StringCell"/>
<config key="org.knime.core.data.def.StringCell">
<entry key="StringCell" type="xstring" value="lyon,nocturne"/>
</config>
</config>
<config key="9">
<entry key="datacell" type="xstring" value="org.knime.core.data.def.StringCell"/>
<config key="org.knime.core.data.def.StringCell">
<entry key="StringCell" type="xstring" value="darse,placenautique,lyon,confluence,architecture,nouveauquartier,pontdesarts"/>
</config>
</config>
<config key="10">
<entry key="datacell" type="xstring" value="org.knime.core.data.def.StringCell"/>
<config key="org.knime.core.data.def.StringCell">
<entry key="StringCell" type="xstring" value="hockey,glace,lhc,leslions,nice,lesaigles,patinoire,charlemagne,lyon,perrache,confluence,sport"/>
</config>
</config>
<config key="11">
<entry key="datacell" type="xstring" value="org.knime.core.data.def.StringCell"/>
<config key="org.knime.core.data.def.StringCell">
<entry key="StringCell" type="xstring" value="lyon,architecture,confluence,poselongue,longexposure,lightpainting,love"/>
</config>
</config>
<config key="12">
<entry key="datacell" type="xstring" value="org.knime.core.data.def.StringCell"/>
<config key="org.knime.core.data.def.StringCell">
<entry key="StringCell" type="xstring" value="architecture,lyon,confluence,ice,poselongue,longexposure"/>
</config>
</config>
<config key="13">
<entry key="datacell" type="xstring" value="org.knime.core.data.def.StringCell"/>
<config key="org.knime.core.data.def.StringCell">
<entry key="StringCell" type="xstring" value="2016,fdl,lyon,deepweb,supermimil"/>
</config>
</config>
</config>
</config>
<config key="column_properties"/>
<config key="meta_data"/>
</config>
<config key="column_spec_5">
<entry key="column_name" type="xstring" value="title"/>
<config key="element_names">
<entry key="array-size" type="xint" value="0"/>
</config>
<config key="column_type">
<entry key="cell_class" type="xstring" value="org.knime.core.data.def.StringCell"/>
</config>
<config key="column_domain">
<config key="possible_values">
<entry key="array-size" type="xint" value="18"/>
<config key="0">
<entry key="datacell" type="xstring" value="org.knime.core.data.def.StringCell"/>
<config key="org.knime.core.data.def.StringCell">
<entry key="StringCell" type="xstring" value="Lyon: Port Rambaud"/>
</config>
</config>
<config key="1">
<entry key="datacell" type="xstring" value="org.knime.core.data.def.StringCell"/>
<config key="org.knime.core.data.def.StringCell">
<entry key="StringCell" type="xstring" value="Lyon: Confluence"/>
</config>
</config>
<config key="2">
<entry key="datacell" type="xstring" value="org.knime.core.data.def.StringCell"/>
<config key="org.knime.core.data.def.StringCell">
<entry key="StringCell" type="xstring" value="Coffee and sun"/>
</config>
</config>
<config key="3">
<entry key="datacell" type="xstring" value="org.knime.core.data.def.StringCell"/>
<config key="org.knime.core.data.def.StringCell">
<entry key="StringCell" type="xstring" value="Lyon - L'autoroute du Soleil au quai Perrache."/>
</config>
</config>
<config key="4">
<entry key="datacell" type="xstring" value="org.knime.core.data.def.StringCell"/>
<config key="org.knime.core.data.def.StringCell">
<entry key="StringCell" type="xstring" value="DSC01072"/>
</config>
</config>
<config key="5">
<entry key="datacell" type="xstring" value="org.knime.core.data.def.StringCell"/>
<config key="org.knime.core.data.def.StringCell">
<entry key="StringCell" type="xstring" value="DSC01073-3"/>
</config>
</config>
<config key="6">
<entry key="datacell" type="xstring" value="org.knime.core.data.def.StringCell"/>
<config key="org.knime.core.data.def.StringCell">
<entry key="StringCell" type="xstring" value="stairs"/>
</config>
</config>
<config key="7">
<entry key="datacell" type="xstring" value="org.knime.core.data.def.StringCell"/>
<config key="org.knime.core.data.def.StringCell">
<entry key="StringCell" type="xstring" value="Hop, couleurs en face"/>
</config>
</config>
<config key="8">
<entry key="datacell" type="xstring" value="org.knime.core.data.def.StringCell"/>
<config key="org.knime.core.data.def.StringCell">
<entry key="StringCell" type="xstring" value="La place nautique de la Confluence (Lyon)"/>
</config>
</config>
<config key="9">
<entry key="datacell" type="xstring" value="org.knime.core.data.def.StringCell"/>
<config key="org.knime.core.data.def.StringCell">
<entry key="StringCell" type="xstring" value="LHC Les Lions VS Nice Les Aigles"/>
</config>
</config>
<config key="10">
<entry key="datacell" type="xstring" value="org.knime.core.data.def.StringCell"/>
<config key="org.knime.core.data.def.StringCell">
<entry key="StringCell" type="xstring" value="From Lyon with ..."/>
</config>
</config>
<config key="11">
<entry key="datacell" type="xstring" value="org.knime.core.data.def.StringCell"/>
<config key="org.knime.core.data.def.StringCell">
<entry key="StringCell" type="xstring" value="Frozen"/>
</config>
</config>
<config key="12">
<entry key="datacell" type="xstring" value="org.knime.core.data.def.StringCell"/>
<config key="org.knime.core.data.def.StringCell">
<entry key="StringCell" type="xstring" value="red light"/>
</config>
</config>
<config key="13">
<entry key="datacell" type="xstring" value="org.knime.core.data.def.StringCell"/>
<config key="org.knime.core.data.def.StringCell">
<entry key="StringCell" type="xstring" value="sphéérique"/>
</config>
</config>
<config key="14">
<entry key="datacell" type="xstring" value="org.knime.core.data.def.StringCell"/>
<config key="org.knime.core.data.def.StringCell">
<entry key="StringCell" type="xstring" value="P1040075"/>
</config>
</config>
<config key="15">
<entry key="datacell" type="xstring" value="org.knime.core.data.def.StringCell"/>
<config key="org.knime.core.data.def.StringCell">
<entry key="StringCell" type="xstring" value="P1040069"/>
</config>
</config>
<config key="16">
<entry key="datacell" type="xstring" value="org.knime.core.data.def.StringCell"/>
<config key="org.knime.core.data.def.StringCell">
<entry key="StringCell" type="xstring" value="deep web"/>
</config>
</config>
<config key="17">
<entry key="datacell" type="xstring" value="org.knime.core.data.def.StringCell"/>
<config key="org.knime.core.data.def.StringCell">
<entry key="StringCell" type="xstring" value="lazr monstr"/>
</config>
</config>
</config>
</config>
<config key="column_properties"/>
<config key="meta_data"/>
</config>
<config key="column_spec_6">
<entry key="column_name" type="xstring" value="date_taken_minute"/>
<config key="element_names">
<entry key="array-size" type="xint" value="0"/>
</config>
<config key="column_type">
<entry key="cell_class" type="xstring" value="org.knime.core.data.def.IntCell"/>
</config>
<config key="column_domain">
<config key="lower_bound">
<entry key="datacell" type="xstring" value="org.knime.core.data.def.IntCell"/>
<config key="org.knime.core.data.def.IntCell">
<entry key="IntCell" type="xint" value="0"/>
</config>
</config>
<config key="upper_bound">
<entry key="datacell" type="xstring" value="org.knime.core.data.def.IntCell"/>
<config key="org.knime.core.data.def.IntCell">
<entry key="IntCell" type="xint" value="2019"/>
</config>
</config>
</config>
<config key="column_properties"/>
<config key="meta_data"/>
</config>
<config key="column_spec_7">
<entry key="column_name" type="xstring" value="date_taken_hour"/>
<config key="element_names">
<entry key="array-size" type="xint" value="0"/>
</config>
<config key="column_type">
<entry key="cell_class" type="xstring" value="org.knime.core.data.def.IntCell"/>
</config>
<config key="column_domain">
<config key="lower_bound">
<entry key="datacell" type="xstring" value="org.knime.core.data.def.IntCell"/>
<config key="org.knime.core.data.def.IntCell">
<entry key="IntCell" type="xint" value="0"/>
</config>
</config>
<config key="upper_bound">
<entry key="datacell" type="xstring" value="org.knime.core.data.def.IntCell"/>
<config key="org.knime.core.data.def.IntCell">
<entry key="IntCell" type="xint" value="2018"/>
</config>
</config>
</config>
<config key="column_properties"/>
<config key="meta_data"/>
</config>
<config key="column_spec_8">
<entry key="column_name" type="xstring" value="date_taken_day"/>
<config key="element_names">
<entry key="array-size" type="xint" value="0"/>
</config>
<config key="column_type">
<entry key="cell_class" type="xstring" value="org.knime.core.data.def.IntCell"/>
</config>
<config key="column_domain">
<config key="lower_bound">
<entry key="datacell" type="xstring" value="org.knime.core.data.def.IntCell"/>
<config key="org.knime.core.data.def.IntCell">
<entry key="IntCell" type="xint" value="1"/>
</config>
</config>
<config key="upper_bound">
<entry key="datacell" type="xstring" value="org.knime.core.data.def.IntCell"/>
<config key="org.knime.core.data.def.IntCell">
<entry key="IntCell" type="xint" value="2013"/>
</config>
</config>
</config>
<config key="column_properties"/>
<config key="meta_data"/>
</config>
<config key="column_spec_9">
<entry key="column_name" type="xstring" value="date_taken_month"/>
<config key="element_names">
<entry key="array-size" type="xint" value="0"/>
</config>
<config key="column_type">
<entry key="cell_class" type="xstring" value="org.knime.core.data.def.IntCell"/>
</config>
<config key="column_domain">
<config key="lower_bound">
<entry key="datacell" type="xstring" value="org.knime.core.data.def.IntCell"/>
<config key="org.knime.core.data.def.IntCell">
<entry key="IntCell" type="xint" value="1"/>
</config>
</config>
<config key="upper_bound">
<entry key="datacell" type="xstring" value="org.knime.core.data.def.IntCell"/>
<config key="org.knime.core.data.def.IntCell">
<entry key="IntCell" type="xint" value="38"/>
</config>
</config>
</config>
<config key="column_properties"/>
<config key="meta_data"/>
</config>
<config key="column_spec_10">
<entry key="column_name" type="xstring" value="date_taken_year"/>
<config key="element_names">
<entry key="array-size" type="xint" value="0"/>
</config>
<config key="column_type">
<entry key="cell_class" type="xstring" value="org.knime.core.data.def.IntCell"/>
</config>
<config key="column_domain">
<config key="lower_bound">
<entry key="datacell" type="xstring" value="org.knime.core.data.def.IntCell"/>
<config key="org.knime.core.data.def.IntCell">
<entry key="IntCell" type="xint" value="1"/>
</config>
</config>
<config key="upper_bound">
<entry key="datacell" type="xstring" value="org.knime.core.data.def.IntCell"/>
<config key="org.knime.core.data.def.IntCell">
<entry key="IntCell" type="xint" value="2238"/>
</config>
</config>
</config>
<config key="column_properties"/>
<config key="meta_data"/>
</config>
<config key="column_spec_11">
<entry key="column_name" type="xstring" value="date_upload_minute"/>
<config key="element_names">
<entry key="array-size" type="xint" value="0"/>
</config>
<config key="column_type">
<entry key="cell_class" type="xstring" value="org.knime.core.data.def.StringCell"/>
</config>
<config key="column_domain">
<config key="possible_values">
<entry key="array-size" type="xint" value="60"/>
<config key="0">
<entry key="datacell" type="xstring" value="org.knime.core.data.def.StringCell"/>
<config key="org.knime.core.data.def.StringCell">
<entry key="StringCell" type="xstring" value="23"/>
</config>
</config>
<config key="1">
<entry key="datacell" type="xstring" value="org.knime.core.data.def.StringCell"/>
<config key="org.knime.core.data.def.StringCell">
<entry key="StringCell" type="xstring" value="52"/>
</config>
</config>
<config key="2">
<entry key="datacell" type="xstring" value="org.knime.core.data.def.StringCell"/>
<config key="org.knime.core.data.def.StringCell">
<entry key="StringCell" type="xstring" value="33"/>
</config>
</config>
<config key="3">
<entry key="datacell" type="xstring" value="org.knime.core.data.def.StringCell"/>
<config key="org.knime.core.data.def.StringCell">
<entry key="StringCell" type="xstring" value="38"/>
</config>
</config>
<config key="4">
<entry key="datacell" type="xstring" value="org.knime.core.data.def.StringCell"/>
<config key="org.knime.core.data.def.StringCell">
<entry key="StringCell" type="xstring" value="1"/>
</config>
</config>
<config key="5">
<entry key="datacell" type="xstring" value="org.knime.core.data.def.StringCell"/>
<config key="org.knime.core.data.def.StringCell">
<entry key="StringCell" type="xstring" value="0"/>
</config>
</config>
<config key="6">
<entry key="datacell" type="xstring" value="org.knime.core.data.def.StringCell"/>
<config key="org.knime.core.data.def.StringCell">
<entry key="StringCell" type="xstring" value="29"/>
</config>
</config>
<config key="7">
<entry key="datacell" type="xstring" value="org.knime.core.data.def.StringCell"/>
<config key="org.knime.core.data.def.StringCell">
<entry key="StringCell" type="xstring" value="28"/>
</config>
</config>
<config key="8">
<entry key="datacell" type="xstring" value="org.knime.core.data.def.StringCell"/>
<config key="org.knime.core.data.def.StringCell">
<entry key="StringCell" type="xstring" value="21"/>
</config>
</config>
<config key="9">
<entry key="datacell" type="xstring" value="org.knime.core.data.def.StringCell"/>
<config key="org.knime.core.data.def.StringCell">
<entry key="StringCell" type="xstring" value="15"/>
</config>
</config>
<config key="10">
<entry key="datacell" type="xstring" value="org.knime.core.data.def.StringCell"/>
<config key="org.knime.core.data.def.StringCell">
<entry key="StringCell" type="xstring" value="45"/>
</config>
</config>
<config key="11">
<entry key="datacell" type="xstring" value="org.knime.core.data.def.StringCell"/>
<config key="org.knime.core.data.def.StringCell">
<entry key="StringCell" type="xstring" value="41"/>
</config>
</config>
<config key="12">
<entry key="datacell" type="xstring" value="org.knime.core.data.def.StringCell"/>
<config key="org.knime.core.data.def.StringCell">
<entry key="StringCell" type="xstring" value="36"/>
</config>
</config>
<config key="13">
<entry key="datacell" type="xstring" value="org.knime.core.data.def.StringCell"/>
<config key="org.knime.core.data.def.StringCell">
<entry key="StringCell" type="xstring" value="35"/>
</config>
</config>
<config key="14">
<entry key="datacell" type="xstring" value="org.knime.core.data.def.StringCell"/>
<config key="org.knime.core.data.def.StringCell">
<entry key="StringCell" type="xstring" value="50"/>
</config>
</config>
<config key="15">
<entry key="datacell" type="xstring" value="org.knime.core.data.def.StringCell"/>
<config key="org.knime.core.data.def.StringCell">
<entry key="StringCell" type="xstring" value="11"/>
</config>
</config>
<config key="16">
<entry key="datacell" type="xstring" value="org.knime.core.data.def.StringCell"/>
<config key="org.knime.core.data.def.StringCell">
<entry key="StringCell" type="xstring" value="4"/>
</config>
</config>
<config key="17">
<entry key="datacell" type="xstring" value="org.knime.core.data.def.StringCell"/>
<config key="org.knime.core.data.def.StringCell">
<entry key="StringCell" type="xstring" value="3"/>
</config>
</config>
<config key="18">
<entry key="datacell" type="xstring" value="org.knime.core.data.def.StringCell"/>
<config key="org.knime.core.data.def.StringCell">
<entry key="StringCell" type="xstring" value="42"/>
</config>
</config>
<config key="19">
<entry key="datacell" type="xstring" value="org.knime.core.data.def.StringCell"/>
<config key="org.knime.core.data.def.StringCell">
<entry key="StringCell" type="xstring" value="18"/>
</config>
</config>
<config key="20">
<entry key="datacell" type="xstring" value="org.knime.core.data.def.StringCell"/>
<config key="org.knime.core.data.def.StringCell">
<entry key="StringCell" type="xstring" value="19"/>
</config>
</config>
<config key="21">
<entry key="datacell" type="xstring" value="org.knime.core.data.def.StringCell"/>
<config key="org.knime.core.data.def.StringCell">
<entry key="StringCell" type="xstring" value="22"/>
</config>
</config>
<config key="22">
<entry key="datacell" type="xstring" value="org.knime.core.data.def.StringCell"/>
<config key="org.knime.core.data.def.StringCell">
<entry key="StringCell" type="xstring" value="37"/>
</config>
</config>
<config key="23">
<entry key="datacell" type="xstring" value="org.knime.core.data.def.StringCell"/>
<config key="org.knime.core.data.def.StringCell">
<entry key="StringCell" type="xstring" value="27"/>
</config>
</config>
<config key="24">
<entry key="datacell" type="xstring" value="org.knime.core.data.def.StringCell"/>
<config key="org.knime.core.data.def.StringCell">
<entry key="StringCell" type="xstring" value="26"/>
</config>
</config>
<config key="25">
<entry key="datacell" type="xstring" value="org.knime.core.data.def.StringCell"/>
<config key="org.knime.core.data.def.StringCell">
<entry key="StringCell" type="xstring" value="25"/>
</config>
</config>
<config key="26">
<entry key="datacell" type="xstring" value="org.knime.core.data.def.StringCell"/>
<config key="org.knime.core.data.def.StringCell">
<entry key="StringCell" type="xstring" value="24"/>
</config>
</config>
<config key="27">
<entry key="datacell" type="xstring" value="org.knime.core.data.def.StringCell"/>
<config key="org.knime.core.data.def.StringCell">
<entry key="StringCell" type="xstring" value="59"/>
</config>
</config>
<config key="28">
<entry key="datacell" type="xstring" value="org.knime.core.data.def.StringCell"/>
<config key="org.knime.core.data.def.StringCell">
<entry key="StringCell" type="xstring" value="58"/>
</config>
</config>
<config key="29">
<entry key="datacell" type="xstring" value="org.knime.core.data.def.StringCell"/>
<config key="org.knime.core.data.def.StringCell">
<entry key="StringCell" type="xstring" value="57"/>
</config>
</config>
<config key="30">
<entry key="datacell" type="xstring" value="org.knime.core.data.def.StringCell"/>
<config key="org.knime.core.data.def.StringCell">
<entry key="StringCell" type="xstring" value="54"/>
</config>
</config>
<config key="31">
<entry key="datacell" type="xstring" value="org.knime.core.data.def.StringCell"/>
<config key="org.knime.core.data.def.StringCell">
<entry key="StringCell" type="xstring" value="48"/>
</config>
</config>
<config key="32">
<entry key="datacell" type="xstring" value="org.knime.core.data.def.StringCell"/>
<config key="org.knime.core.data.def.StringCell">
<entry key="StringCell" type="xstring" value="10"/>
</config>
</config>
<config key="33">
<entry key="datacell" type="xstring" value="org.knime.core.data.def.StringCell"/>
<config key="org.knime.core.data.def.StringCell">
<entry key="StringCell" type="xstring" value="5"/>
</config>
</config>
<config key="34">
<entry key="datacell" type="xstring" value="org.knime.core.data.def.StringCell"/>
<config key="org.knime.core.data.def.StringCell">
<entry key="StringCell" type="xstring" value="12"/>
</config>
</config>
<config key="35">
<entry key="datacell" type="xstring" value="org.knime.core.data.def.StringCell"/>
<config key="org.knime.core.data.def.StringCell">
<entry key="StringCell" type="xstring" value="8"/>
</config>
</config>
<config key="36">
<entry key="datacell" type="xstring" value="org.knime.core.data.def.StringCell"/>
<config key="org.knime.core.data.def.StringCell">
<entry key="StringCell" type="xstring" value="56"/>
</config>
</config>
<config key="37">
<entry key="datacell" type="xstring" value="org.knime.core.data.def.StringCell"/>
<config key="org.knime.core.data.def.StringCell">
<entry key="StringCell" type="xstring" value="16"/>
</config>
</config>
<config key="38">
<entry key="datacell" type="xstring" value="org.knime.core.data.def.StringCell"/>
<config key="org.knime.core.data.def.StringCell">
<entry key="StringCell" type="xstring" value="13"/>
</config>
</config>
<config key="39">
<entry key="datacell" type="xstring" value="org.knime.core.data.def.StringCell"/>
<config key="org.knime.core.data.def.StringCell">
<entry key="StringCell" type="xstring" value="55"/>
</config>
</config>
<config key="40">
<entry key="datacell" type="xstring" value="org.knime.core.data.def.StringCell"/>
<config key="org.knime.core.data.def.StringCell">
<entry key="StringCell" type="xstring" value="6"/>
</config>
</config>
<config key="41">
<entry key="datacell" type="xstring" value="org.knime.core.data.def.StringCell"/>
<config key="org.knime.core.data.def.StringCell">
<entry key="StringCell" type="xstring" value="47"/>
</config>
</config>
<config key="42">
<entry key="datacell" type="xstring" value="org.knime.core.data.def.StringCell"/>
<config key="org.knime.core.data.def.StringCell">
<entry key="StringCell" type="xstring" value="40"/>
</config>
</config>
<config key="43">
<entry key="datacell" type="xstring" value="org.knime.core.data.def.StringCell"/>
<config key="org.knime.core.data.def.StringCell">
<entry key="StringCell" type="xstring" value="34"/>
</config>
</config>
<config key="44">
<entry key="datacell" type="xstring" value="org.knime.core.data.def.StringCell"/>
<config key="org.knime.core.data.def.StringCell">
<entry key="StringCell" type="xstring" value="2"/>
</config>
</config>
<config key="45">
<entry key="datacell" type="xstring" value="org.knime.core.data.def.StringCell"/>
<config key="org.knime.core.data.def.StringCell">
<entry key="StringCell" type="xstring" value="43"/>
</config>
</config>
<config key="46">
<entry key="datacell" type="xstring" value="org.knime.core.data.def.StringCell"/>
<config key="org.knime.core.data.def.StringCell">
<entry key="StringCell" type="xstring" value="14"/>
</config>
</config>
<config key="47">
<entry key="datacell" type="xstring" value="org.knime.core.data.def.StringCell"/>
<config key="org.knime.core.data.def.StringCell">
<entry key="StringCell" type="xstring" value="30"/>
</config>
</config>
<config key="48">
<entry key="datacell" type="xstring" value="org.knime.core.data.def.StringCell"/>
<config key="org.knime.core.data.def.StringCell">
<entry key="StringCell" type="xstring" value="39"/>
</config>
</config>
<config key="49">
<entry key="datacell" type="xstring" value="org.knime.core.data.def.StringCell"/>
<config key="org.knime.core.data.def.StringCell">
<entry key="StringCell" type="xstring" value="17"/>
</config>
</config>
<config key="50">
<entry key="datacell" type="xstring" value="org.knime.core.data.def.StringCell"/>
<config key="org.knime.core.data.def.StringCell">
<entry key="StringCell" type="xstring" value="32"/>
</config>
</config>
<config key="51">
<entry key="datacell" type="xstring" value="org.knime.core.data.def.StringCell"/>
<config key="org.knime.core.data.def.StringCell">
<entry key="StringCell" type="xstring" value="31"/>
</config>
</config>
<config key="52">
<entry key="datacell" type="xstring" value="org.knime.core.data.def.StringCell"/>
<config key="org.knime.core.data.def.StringCell">
<entry key="StringCell" type="xstring" value="53"/>
</config>
</config>
<config key="53">
<entry key="datacell" type="xstring" value="org.knime.core.data.def.StringCell"/>
<config key="org.knime.core.data.def.StringCell">
<entry key="StringCell" type="xstring" value="51"/>
</config>
</config>
<config key="54">
<entry key="datacell" type="xstring" value="org.knime.core.data.def.StringCell"/>
<config key="org.knime.core.data.def.StringCell">
<entry key="StringCell" type="xstring" value="49"/>
</config>
</config>
<config key="55">
<entry key="datacell" type="xstring" value="org.knime.core.data.def.StringCell"/>
<config key="org.knime.core.data.def.StringCell">
<entry key="StringCell" type="xstring" value="44"/>
</config>
</config>
<config key="56">
<entry key="datacell" type="xstring" value="org.knime.core.data.def.StringCell"/>
<config key="org.knime.core.data.def.StringCell">
<entry key="StringCell" type="xstring" value="20"/>
</config>
</config>
<config key="57">
<entry key="datacell" type="xstring" value="org.knime.core.data.def.StringCell"/>
<config key="org.knime.core.data.def.StringCell">
<entry key="StringCell" type="xstring" value="9"/>
</config>
</config>
<config key="58">
<entry key="datacell" type="xstring" value="org.knime.core.data.def.StringCell"/>
<config key="org.knime.core.data.def.StringCell">
<entry key="StringCell" type="xstring" value="7"/>
</config>
</config>
<config key="59">
<entry key="datacell" type="xstring" value="org.knime.core.data.def.StringCell"/>
<config key="org.knime.core.data.def.StringCell">
<entry key="StringCell" type="xstring" value="46"/>
</config>
</config>
</config>
</config>
<config key="column_properties"/>
<config key="meta_data"/>
</config>
<config key="column_spec_12">
<entry key="column_name" type="xstring" value="date_upload_hour"/>
<config key="element_names">
<entry key="array-size" type="xint" value="0"/>
</config>
<config key="column_type">
<entry key="cell_class" type="xstring" value="org.knime.core.data.def.StringCell"/>
</config>
<config key="column_domain">
<config key="possible_values">
<entry key="array-size" type="xint" value="45"/>
<config key="0">
<entry key="datacell" type="xstring" value="org.knime.core.data.def.StringCell"/>
<config key="org.knime.core.data.def.StringCell">
<entry key="StringCell" type="xstring" value="20"/>
</config>
</config>
<config key="1">
<entry key="datacell" type="xstring" value="org.knime.core.data.def.StringCell"/>
<config key="org.knime.core.data.def.StringCell">
<entry key="StringCell" type="xstring" value="17"/>
</config>
</config>
<config key="2">
<entry key="datacell" type="xstring" value="org.knime.core.data.def.StringCell"/>
<config key="org.knime.core.data.def.StringCell">
<entry key="StringCell" type="xstring" value="12"/>
</config>
</config>
<config key="3">
<entry key="datacell" type="xstring" value="org.knime.core.data.def.StringCell"/>
<config key="org.knime.core.data.def.StringCell">
<entry key="StringCell" type="xstring" value="10"/>
</config>
</config>
<config key="4">
<entry key="datacell" type="xstring" value="org.knime.core.data.def.StringCell"/>
<config key="org.knime.core.data.def.StringCell">
<entry key="StringCell" type="xstring" value="21"/>
</config>
</config>
<config key="5">
<entry key="datacell" type="xstring" value="org.knime.core.data.def.StringCell"/>
<config key="org.knime.core.data.def.StringCell">
<entry key="StringCell" type="xstring" value="18"/>
</config>
</config>
<config key="6">
<entry key="datacell" type="xstring" value="org.knime.core.data.def.StringCell"/>
<config key="org.knime.core.data.def.StringCell">
<entry key="StringCell" type="xstring" value="16"/>
</config>
</config>
<config key="7">
<entry key="datacell" type="xstring" value="org.knime.core.data.def.StringCell"/>
<config key="org.knime.core.data.def.StringCell">
<entry key="StringCell" type="xstring" value="14"/>
</config>
</config>
<config key="8">
<entry key="datacell" type="xstring" value="org.knime.core.data.def.StringCell"/>
<config key="org.knime.core.data.def.StringCell">
<entry key="StringCell" type="xstring" value="9"/>
</config>
</config>
<config key="9">
<entry key="datacell" type="xstring" value="org.knime.core.data.def.StringCell"/>
<config key="org.knime.core.data.def.StringCell">
<entry key="StringCell" type="xstring" value="4"/>
</config>
</config>
<config key="10">
<entry key="datacell" type="xstring" value="org.knime.core.data.def.StringCell"/>
<config key="org.knime.core.data.def.StringCell">
<entry key="StringCell" type="xstring" value="1"/>
</config>
</config>
<config key="11">
<entry key="datacell" type="xstring" value="org.knime.core.data.def.StringCell"/>
<config key="org.knime.core.data.def.StringCell">
<entry key="StringCell" type="xstring" value="23"/>
</config>
</config>
<config key="12">
<entry key="datacell" type="xstring" value="org.knime.core.data.def.StringCell"/>
<config key="org.knime.core.data.def.StringCell">
<entry key="StringCell" type="xstring" value="15"/>
</config>
</config>
<config key="13">
<entry key="datacell" type="xstring" value="org.knime.core.data.def.StringCell"/>
<config key="org.knime.core.data.def.StringCell">
<entry key="StringCell" type="xstring" value="7"/>
</config>
</config>
<config key="14">
<entry key="datacell" type="xstring" value="org.knime.core.data.def.StringCell"/>
<config key="org.knime.core.data.def.StringCell">
<entry key="StringCell" type="xstring" value="22"/>
</config>
</config>
<config key="15">
<entry key="datacell" type="xstring" value="org.knime.core.data.def.StringCell"/>
<config key="org.knime.core.data.def.StringCell">
<entry key="StringCell" type="xstring" value="19"/>
</config>
</config>
<config key="16">
<entry key="datacell" type="xstring" value="org.knime.core.data.def.StringCell"/>
<config key="org.knime.core.data.def.StringCell">
<entry key="StringCell" type="xstring" value="3"/>
</config>
</config>
<config key="17">
<entry key="datacell" type="xstring" value="org.knime.core.data.def.StringCell"/>
<config key="org.knime.core.data.def.StringCell">
<entry key="StringCell" type="xstring" value="11"/>
</config>
</config>
<config key="18">
<entry key="datacell" type="xstring" value="org.knime.core.data.def.StringCell"/>
<config key="org.knime.core.data.def.StringCell">
<entry key="StringCell" type="xstring" value="2"/>
</config>
</config>
<config key="19">
<entry key="datacell" type="xstring" value="org.knime.core.data.def.StringCell"/>
<config key="org.knime.core.data.def.StringCell">
<entry key="StringCell" type="xstring" value="0"/>
</config>
</config>
<config key="20">
<entry key="datacell" type="xstring" value="org.knime.core.data.def.StringCell"/>
<config key="org.knime.core.data.def.StringCell">
<entry key="StringCell" type="xstring" value="13"/>
</config>
</config>
<config key="21">
<entry key="datacell" type="xstring" value="org.knime.core.data.def.StringCell"/>
<config key="org.knime.core.data.def.StringCell">
<entry key="StringCell" type="xstring" value="8"/>
</config>
</config>
<config key="22">
<entry key="datacell" type="xstring" value="org.knime.core.data.def.StringCell"/>
<config key="org.knime.core.data.def.StringCell">
<entry key="StringCell" type="xstring" value="6"/>
</config>
</config>
<config key="23">
<entry key="datacell" type="xstring" value="org.knime.core.data.def.StringCell"/>
<config key="org.knime.core.data.def.StringCell">
<entry key="StringCell" type="xstring" value="5"/>
</config>
</config>
<config key="24">
<entry key="datacell" type="xstring" value="org.knime.core.data.def.StringCell"/>
<config key="org.knime.core.data.def.StringCell">
<entry key="StringCell" type="xstring" value="43"/>
</config>
</config>
<config key="25">
<entry key="datacell" type="xstring" value="org.knime.core.data.def.StringCell"/>
<config key="org.knime.core.data.def.StringCell">
<entry key="StringCell" type="xstring" value="26"/>
</config>
</config>
<config key="26">
<entry key="datacell" type="xstring" value="org.knime.core.data.def.StringCell"/>
<config key="org.knime.core.data.def.StringCell">
<entry key="StringCell" type="xstring" value="27"/>
</config>
</config>
<config key="27">
<entry key="datacell" type="xstring" value="org.knime.core.data.def.StringCell"/>
<config key="org.knime.core.data.def.StringCell">
<entry key="StringCell" type="xstring" value="47"/>
</config>
</config>
<config key="28">
<entry key="datacell" type="xstring" value="org.knime.core.data.def.StringCell"/>
<config key="org.knime.core.data.def.StringCell">
<entry key="StringCell" type="xstring" value="32"/>
</config>
</config>
<config key="29">
<entry key="datacell" type="xstring" value="org.knime.core.data.def.StringCell"/>
<config key="org.knime.core.data.def.StringCell">
<entry key="StringCell" type="xstring" value="46"/>
</config>
</config>
<config key="30">
<entry key="datacell" type="xstring" value="org.knime.core.data.def.StringCell"/>
<config key="org.knime.core.data.def.StringCell">
<entry key="StringCell" type="xstring" value="49"/>
</config>
</config>
<config key="31">
<entry key="datacell" type="xstring" value="org.knime.core.data.def.StringCell"/>
<config key="org.knime.core.data.def.StringCell">
<entry key="StringCell" type="xstring" value="44"/>
</config>
</config>
<config key="32">
<entry key="datacell" type="xstring" value="org.knime.core.data.def.StringCell"/>
<config key="org.knime.core.data.def.StringCell">
<entry key="StringCell" type="xstring" value="28"/>
</config>
</config>
<config key="33">
<entry key="datacell" type="xstring" value="org.knime.core.data.def.StringCell"/>
<config key="org.knime.core.data.def.StringCell">
<entry key="StringCell" type="xstring" value=".!"/>
</config>
</config>
<config key="34">
<entry key="datacell" type="xstring" value="org.knime.core.data.def.StringCell"/>
<config key="org.knime.core.data.def.StringCell">
<entry key="StringCell" type="xstring" value="38"/>
</config>
</config>
<config key="35">
<entry key="datacell" type="xstring" value="org.knime.core.data.def.StringCell"/>
<config key="org.knime.core.data.def.StringCell">
<entry key="StringCell" type="xstring" value="36"/>
</config>
</config>
<config key="36">
<entry key="datacell" type="xstring" value="org.knime.core.data.def.StringCell"/>
<config key="org.knime.core.data.def.StringCell">
<entry key="StringCell" type="xstring" value="54"/>
</config>
</config>
<config key="37">
<entry key="datacell" type="xstring" value="org.knime.core.data.def.StringCell"/>
<config key="org.knime.core.data.def.StringCell">
<entry key="StringCell" type="xstring" value="42"/>
</config>
</config>
<config key="38">
<entry key="datacell" type="xstring" value="org.knime.core.data.def.StringCell"/>
<config key="org.knime.core.data.def.StringCell">
<entry key="StringCell" type="xstring" value="33"/>
</config>
</config>
<config key="39">
<entry key="datacell" type="xstring" value="org.knime.core.data.def.StringCell"/>
<config key="org.knime.core.data.def.StringCell">
<entry key="StringCell" type="xstring" value="24"/>
</config>
</config>
<config key="40">
<entry key="datacell" type="xstring" value="org.knime.core.data.def.StringCell"/>
<config key="org.knime.core.data.def.StringCell">
<entry key="StringCell" type="xstring" value="53"/>
</config>
</config>
<config key="41">
<entry key="datacell" type="xstring" value="org.knime.core.data.def.StringCell"/>
<config key="org.knime.core.data.def.StringCell">
<entry key="StringCell" type="xstring" value="-)"/>
</config>
</config>
<config key="42">
<entry key="datacell" type="xstring" value="org.knime.core.data.def.StringCell"/>
<config key="org.knime.core.data.def.StringCell">
<entry key="StringCell" type="xstring" value="29"/>
</config>
</config>
<config key="43">
<entry key="datacell" type="xstring" value="org.knime.core.data.def.StringCell"/>
<config key="org.knime.core.data.def.StringCell">
<entry key="StringCell" type="xstring" value="45"/>
</config>
</config>
<config key="44">
<entry key="datacell" type="xstring" value="org.knime.core.data.def.StringCell"/>
<config key="org.knime.core.data.def.StringCell">
<entry key="StringCell" type="xstring" value="25"/>
</config>
</config>
</config>
</config>
<config key="column_properties"/>
<config key="meta_data"/>
</config>
<config key="column_spec_13">
<entry key="column_name" type="xstring" value="date_upload_day"/>
<config key="element_names">
<entry key="array-size" type="xint" value="0"/>
</config>
<config key="column_type">
<entry key="cell_class" type="xstring" value="org.knime.core.data.def.IntCell"/>
</config>
<config key="column_domain">
<config key="lower_bound">
<entry key="datacell" type="xstring" value="org.knime.core.data.def.IntCell"/>
<config key="org.knime.core.data.def.IntCell">
<entry key="IntCell" type="xint" value="0"/>
</config>
</config>
<config key="upper_bound">
<entry key="datacell" type="xstring" value="org.knime.core.data.def.IntCell"/>
<config key="org.knime.core.data.def.IntCell">
<entry key="IntCell" type="xint" value="40"/>
</config>
</config>
</config>
<config key="column_properties"/>
<config key="meta_data"/>
</config>
<config key="column_spec_14">
<entry key="column_name" type="xstring" value="date_upload_month"/>
<config key="element_names">
<entry key="array-size" type="xint" value="0"/>
</config>
<config key="column_type">
<entry key="cell_class" type="xstring" value="org.knime.core.data.def.IntCell"/>
</config>
<config key="column_domain">
<config key="lower_bound">
<entry key="datacell" type="xstring" value="org.knime.core.data.def.IntCell"/>
<config key="org.knime.core.data.def.IntCell">
<entry key="IntCell" type="xint" value="1"/>
</config>
</config>
<config key="upper_bound">
<entry key="datacell" type="xstring" value="org.knime.core.data.def.IntCell"/>
<config key="org.knime.core.data.def.IntCell">
<entry key="IntCell" type="xint" value="51"/>
</config>
</config>
</config>
<config key="column_properties"/>
<config key="meta_data"/>
</config>
<config key="column_spec_15">
<entry key="column_name" type="xstring" value="date_upload_year"/>
<config key="element_names">
<entry key="array-size" type="xint" value="0"/>
</config>
<config key="column_type">
<entry key="cell_class" type="xstring" value="org.knime.core.data.def.IntCell"/>
</config>
<config key="column_domain">
<config key="lower_bound">
<entry key="datacell" type="xstring" value="org.knime.core.data.def.IntCell"/>
<config key="org.knime.core.data.def.IntCell">
<entry key="IntCell" type="xint" value="1"/>
</config>
</config>
<config key="upper_bound">
<entry key="datacell" type="xstring" value="org.knime.core.data.def.IntCell"/>
<config key="org.knime.core.data.def.IntCell">
<entry key="IntCell" type="xint" value="2019"/>
</config>
</config>
</config>
<config key="column_properties"/>
<config key="meta_data"/>
</config>
</config>
